stattotex/__init__.py
stattotex/stattotex.py
stattotex-0.1.3.dist-info/licenses/LICENSE
stattotex-0.1.3.dist-info/METADATA
stattotex-0.1.3.dist-info/WHEEL
stattotex-0.1.3.dist-info/top_level.txt
stattotex-0.1.3.dist-info/RECORD
