Metadata-Version: 2.4
Name: stattotex
Version: 0.1.3
Summary: A simple function for automatically updating LaTeX documents with numbers from Python.
Home-page: https://github.com/ijyliu/stattotex-python
Author: Isaac Liu
Author-email: ijyliu@gmail.com
License: MIT
Classifier: Programming Language :: Python :: 3
Classifier: Operating System :: OS Independent
License-File: LICENSE
Dynamic: author
Dynamic: author-email
Dynamic: classifier
Dynamic: description
Dynamic: description-content-type
Dynamic: home-page
Dynamic: license
Dynamic: license-file
Dynamic: summary
